__init__.py
generate.py
is_prime.py
words_count.py
tuzikmediatools-1.2.dist-info/METADATA
tuzikmediatools-1.2.dist-info/WHEEL
tuzikmediatools-1.2.dist-info/top_level.txt
tuzikmediatools-1.2.dist-info/RECORD
