Metadata-Version: 2.1
Name: tuzikmediatools
Version: 1.2
Home-page: https://github.com/TuzikMedia/tuzikmediatools
Author: rimmirk
Author-email: xktrimall@gmail.com
Classifier: Programming Language :: Python :: 3
Classifier: License :: OSI Approved :: MIT License
Classifier: Operating System :: OS Independent
Requires-Python: >=3.6
